tapioca_stripe/__init__.py
tapioca_stripe/tapioca_stripe.py
tapioca_stripe/resource_mapping/__init__.py
tapioca_stripe/resource_mapping/balance.py
tapioca_stripe/resource_mapping/charges.py
tapioca_stripe/resource_mapping/customers.py
tapioca_stripe/resource_mapping/disputes.py
tapioca_stripe/resource_mapping/events.py
tapioca_stripe/resource_mapping/file_links.py
tapioca_stripe/resource_mapping/files.py
tapioca_stripe/resource_mapping/payment_intents.py
tapioca_stripe/resource_mapping/payouts.py
tapioca_stripe/resource_mapping/products.py
tapioca_stripe/resource_mapping/refunds.py
tapioca_stripe/resource_mapping/tokens.py
tests/__init__.py
tests/test_tapioca_stripe.py
tapioca_stripe-0.2.dist-info/LICENSE
tapioca_stripe-0.2.dist-info/METADATA
tapioca_stripe-0.2.dist-info/WHEEL
tapioca_stripe-0.2.dist-info/top_level.txt
tapioca_stripe-0.2.dist-info/RECORD
